LICENSE
README.md
setup.py
benchmark/__init__.py
benchmark/backup_googlenet.py
benchmark/backup_poolformer.py
benchmark/test_alexnet.py
benchmark/test_convnext.py
benchmark/test_crossformer.py
benchmark/test_cswin.py
benchmark/test_densenet.py
benchmark/test_ghostnet.py
benchmark/test_inception.py
benchmark/test_mlp_mixer.py
benchmark/test_mnasnet.py
benchmark/test_mobilenet.py
benchmark/test_pvt.py
benchmark/test_res2net.py
benchmark/test_res_mlp.py
benchmark/test_resnet.py
benchmark/test_rexnet.py
benchmark/test_shufflenet.py
benchmark/test_squeezenet.py
benchmark/test_swin_transformer.py
benchmark/test_uniformer.py
benchmark/test_vision_transformer.py
flowvision/__init__.py
flowvision/version.py
flowvision.egg-info/PKG-INFO
flowvision.egg-info/SOURCES.txt
flowvision.egg-info/dependency_links.txt
flowvision.egg-info/requires.txt
flowvision.egg-info/top_level.txt
flowvision/data/__init__.py
flowvision/data/auto_augment.py
flowvision/data/constants.py
flowvision/data/mixup.py
flowvision/data/random_erasing.py
flowvision/data/transforms_factory.py
flowvision/datasets/__init__.py
flowvision/datasets/caltech.py
flowvision/datasets/celeba.py
flowvision/datasets/cifar.py
flowvision/datasets/cityscapes.py
flowvision/datasets/clevr.py
flowvision/datasets/coco.py
flowvision/datasets/country211.py
flowvision/datasets/dtd.py
flowvision/datasets/eurosat.py
flowvision/datasets/fakedata.py
flowvision/datasets/fer2013.py
flowvision/datasets/fgvc_aircraft.py
flowvision/datasets/flickr.py
flowvision/datasets/flowers102.py
flowvision/datasets/folder.py
flowvision/datasets/food101.py
flowvision/datasets/gtsrb.py
flowvision/datasets/imagenet.py
flowvision/datasets/inaturalist.py
flowvision/datasets/kitti.py
flowvision/datasets/lfw.py
flowvision/datasets/lsun.py
flowvision/datasets/mnist.py
flowvision/datasets/omniglot.py
flowvision/datasets/oxford_iiit_pet.py
flowvision/datasets/pcam.py
flowvision/datasets/phototour.py
flowvision/datasets/places365.py
flowvision/datasets/rendered_sst2.py
flowvision/datasets/sbd.py
flowvision/datasets/sbu.py
flowvision/datasets/semeion.py
flowvision/datasets/stanford_cars.py
flowvision/datasets/stl10.py
