Metadata-Version: 2.1
Name: flowvision
Version: 0.2.2
Summary: oneflow vision codebase
Home-page: https://github.com/Oneflow-Inc/vision
Author: flow vision contributors
Author-email: rentianhe@oneflow.org
License: BSD
Keywords: computer vision
Platform: any
Classifier: License :: OSI Approved :: MIT License
Classifier: Programming Language :: Python :: 3
Classifier: Programming Language :: Python :: 3.5
Classifier: Programming Language :: Python :: 3.6
Classifier: Programming Language :: Python :: 3.7
Classifier: Programming Language :: Python :: 3.8
Classifier: Programming Language :: Python :: 3.9
Classifier: Intended Audience :: Developers
Classifier: Operating System :: OS Independent
